seamm_exec/__init__.py
seamm_exec/_version.py
seamm_exec/base.py
seamm_exec/computational_environment.py
seamm_exec/docker.py
seamm_exec/exec_flowchart.py
seamm_exec/local.py
seamm_exec/py.typed
seamm_exec/seamm_exec.py
seamm_exec-2025.10.23.dist-info/licenses/LICENSE
tests/__init__.py
tests/test_seamm_exec.py
seamm_exec-2025.10.23.dist-info/METADATA
seamm_exec-2025.10.23.dist-info/WHEEL
seamm_exec-2025.10.23.dist-info/entry_points.txt
seamm_exec-2025.10.23.dist-info/top_level.txt
seamm_exec-2025.10.23.dist-info/RECORD
